odoo/addons/event_activity/README.rst
odoo/addons/event_activity/__init__.py
odoo/addons/event_activity/__manifest__.py
odoo/addons/event_activity/i18n/es.po
odoo/addons/event_activity/i18n/event_activity.pot
odoo/addons/event_activity/models/__init__.py
odoo/addons/event_activity/models/event.py
odoo/addons/event_activity/readme/DESCRIPTION.rst
odoo/addons/event_activity/readme/ROADMAP.rst
odoo/addons/event_activity/static/description/icon.png
odoo/addons/event_activity/static/description/index.html
odoo/addons/event_activity/views/event_event.xml
odoo/addons/event_activity/views/event_registration.xml
odoo12_addon_event_activity-12.0.1.0.1.dist-info/METADATA
odoo12_addon_event_activity-12.0.1.0.1.dist-info/WHEEL
odoo12_addon_event_activity-12.0.1.0.1.dist-info/top_level.txt
odoo12_addon_event_activity-12.0.1.0.1.dist-info/RECORD
